chess_cv/__init__.py
chess_cv/__main__.py
chess_cv/cli.py
chess_cv/constants.py
chess_cv/data.py
chess_cv/evaluate.py
chess_cv/model.py
chess_cv/preprocessing.py
chess_cv/sweep.py
chess_cv/test.py
chess_cv/train.py
chess_cv/upload.py
chess_cv/utils.py
chess_cv/visualize.py
chess_cv/wandb_utils.py
chess_cv/weights/__init__.py
chess_cv/weights/arrows.safetensors
chess_cv/weights/pieces.safetensors
chess_cv/weights/snap.safetensors
chess_cv-0.7.2.dist-info/WHEEL
chess_cv-0.7.2.dist-info/entry_points.txt
chess_cv-0.7.2.dist-info/METADATA
chess_cv-0.7.2.dist-info/RECORD
