Metadata-Version: 2.3
Name: chess-cv
Version: 0.7.2
Summary: CNN-based chess piece classifier
Author: S1M0N38
Author-email: S1M0N38 <bertolottosimone@gmail.com>
Classifier: License :: OSI Approved :: MIT License
Classifier: Programming Language :: Python :: 3.13
Requires-Dist: click>=8.3.0
Requires-Dist: mlx>=0.24.0
Requires-Dist: numpy>=2.0.0
Requires-Dist: pillow>=11.3.0
Requires-Dist: pyyaml>=6.0.3
Requires-Python: >=3.13
Project-URL: Changelog, https://github.com/S1M0N38/chess-cv/blob/main/CHANGELOG.md
Project-URL: Homepage, https://github.com/S1M0N38/chess-cv
Project-URL: Issues, https://github.com/S1M0N38/chess-cv/issues
Project-URL: Repository, https://github.com/S1M0N38/chess-cv
